pyqweather/__init__.py
pyqweather/auth/__init__.py
pyqweather/factories/__init__.py
pyqweather/factories/qweather_factory.py
pyqweather/packages/__init__.py
pyqweather/packages/air/__init__.py
pyqweather/packages/air/air_daily.py
pyqweather/packages/air/air_now.py
pyqweather/packages/air_quality/__init__.py
pyqweather/packages/air_quality/airquality_now.py
pyqweather/packages/air_quality/airquality_station.py
pyqweather/packages/astronomy/__init__.py
pyqweather/packages/astronomy/moon.py
pyqweather/packages/astronomy/solar_elevation_angle.py
pyqweather/packages/astronomy/sun.py
pyqweather/packages/geo/__init__.py
pyqweather/packages/geo/city_lookup.py
pyqweather/packages/geo/city_top.py
pyqweather/packages/geo/poi_lookup.py
pyqweather/packages/geo/poi_range.py
pyqweather/packages/grid_weather/__init__.py
pyqweather/packages/grid_weather/grid_weather_daily.py
pyqweather/packages/grid_weather/grid_weather_hourly.py
pyqweather/packages/grid_weather/grid_weather_now.py
pyqweather/packages/indices/__init__.py
pyqweather/packages/indices/indices_daily.py
pyqweather/packages/minutely/__init__.py
pyqweather/packages/minutely/minutely_5m.py
pyqweather/packages/ocean/__init__.py
pyqweather/packages/ocean/currents.py
pyqweather/packages/ocean/tide.py
pyqweather/packages/solar_radiation/__init__.py
pyqweather/packages/solar_radiation/solar_radiation_hourly.py
pyqweather/packages/time_machine/__init__.py
pyqweather/packages/time_machine/historical_air.py
pyqweather/packages/time_machine/historical_weather.py
pyqweather/packages/tropical_cyclone/__init__.py
pyqweather/packages/tropical_cyclone/storm_forecast.py
pyqweather/packages/tropical_cyclone/storm_list.py
pyqweather/packages/tropical_cyclone/storm_track.py
pyqweather/packages/weather/__init__.py
pyqweather/packages/weather/weather_daily.py
pyqweather/packages/weather/weather_hourly.py
pyqweather/packages/weather/weather_now.py
pyqweather/packages/weather_warning/__init__.py
pyqweather-1.0.6.dist-info/LICENSE
pyqweather-1.0.6.dist-info/METADATA
pyqweather-1.0.6.dist-info/WHEEL
pyqweather-1.0.6.dist-info/top_level.txt
pyqweather-1.0.6.dist-info/RECORD
