Metadata-Version: 2.1
Name: pyqweather
Version: 1.0.6
Summary: 和风天气 api for python3
Home-page: https://github.com/imaxu/py-qweather
Author: xuwh
Author-email: xuwhdev@gmail.com
License: UNKNOWN
Platform: UNKNOWN
Requires-Python: >=3.6
License-File: LICENSE
Requires-Dist: requests ==2.32.3
